pylinreg/__init__.py
pylinreg/_pylinreg.py
pylinreg-1.0.1.dist-info/LICENSE
pylinreg-1.0.1.dist-info/METADATA
pylinreg-1.0.1.dist-info/WHEEL
pylinreg-1.0.1.dist-info/top_level.txt
pylinreg-1.0.1.dist-info/RECORD
