Metadata-Version: 2.1
Name: pylinreg
Version: 1.0.1
Summary: Linear Regression Model with only Python Standard Library based on Ordinary Least Squares (OLS) Method
Home-page: https://github.com/richardvecsey/PyLinReg
Author: Richárd Ádám Vécsey Dr.
License: MIT
Platform: UNKNOWN
Classifier: License :: OSI Approved :: MIT License
Classifier: Programming Language :: Python :: 3
Classifier: Operating System :: OS Independent
Requires-Python: >=3.6
